giget/__init__.py
giget/cli.py
giget/core.py
giget/help.py
giget/list.py
giget-0.4.18.dist-info/METADATA
giget-0.4.18.dist-info/WHEEL
giget-0.4.18.dist-info/entry_points.txt
giget-0.4.18.dist-info/top_level.txt
giget-0.4.18.dist-info/RECORD
