Metadata-Version: 2.4
Name: giget
Version: 0.4.18
Summary: A simple tool to download files/folders from GitHub repositories
Author-email: Ronit Naik <ronitnaik122@gmail.com>
License: LICENSE
Project-URL: Homepage, https://github.com/RonitNaik122/GitLoad
Project-URL: Repository, https://github.com/RonitNaik122/GitLoad
Project-URL: Issues, https://github.com/RonitNaik122/GitLoad/issues
Keywords: github,download,cli,git
Classifier: Development Status :: 3 - Alpha
Classifier: Intended Audience :: Developers
Classifier: License :: OSI Approved :: MIT License
Classifier: Operating System :: OS Independent
Classifier: Programming Language :: Python :: 3
Classifier: Programming Language :: Python :: 3.11
Classifier: Programming Language :: Python :: 3.12
Requires-Python: >=3.11
Requires-Dist: requests
